sonos/__init__.py
sonos/cli.py
sonos/decorators.py
sonos/settings.py
sonos/api/__init__.py
sonos/api/auth.py
sonos/api/control.py
sonos/commands/__init__.py
sonos/commands/config.py
sonos/commands/get.py
sonos/commands/login.py
sonos/commands/logout.py
sonos/commands/next.py
sonos/commands/pause.py
sonos/commands/play.py
sonos/commands/prev.py
sonos/commands/set.py
sonos/commands/status.py
sonos/commands/volume.py
sonos/commands/templates/fail.html
sonos/commands/templates/ok.html
sonos/config/__init__.py
sonos/config/active_group_store.py
sonos/config/active_household_store.py
sonos/config/config_store.py
sonos/config/creds_store.py
sonos/config/local_store.py
sonos_cli-0.3.7.dist-info/LICENSE
sonos_cli-0.3.7.dist-info/METADATA
sonos_cli-0.3.7.dist-info/WHEEL
sonos_cli-0.3.7.dist-info/entry_points.txt
sonos_cli-0.3.7.dist-info/top_level.txt
sonos_cli-0.3.7.dist-info/RECORD
