Metadata-Version: 2.1
Name: sonos-cli
Version: 0.3.7
Summary: Sonos Command-Line Tools
Home-page: https://github.com/bwilczynski/sonos-cli
Author: Bartlomiej Wilczynski
Author-email: me@bwilczynski.com
License: UNKNOWN
Platform: UNKNOWN
Requires-Python: >=3.0
Requires-Dist: click
Requires-Dist: requests
Requires-Dist: requests-oauthlib
Requires-Dist: tabulate
